itchatui/__init__.py
itchatui-0.0.0.dist-info/DESCRIPTION.rst
itchatui-0.0.0.dist-info/METADATA
itchatui-0.0.0.dist-info/RECORD
itchatui-0.0.0.dist-info/WHEEL
itchatui-0.0.0.dist-info/metadata.json
itchatui-0.0.0.dist-info/top_level.txt
