Metadata-Version: 2.0
Name: itchatui
Version: 0.0.0
Summary: A wechat ui based on qt
Home-page: https://github.com/littlecodersh/itchatui
Author: LittleCoder
Author-email: i7meavnktqegm1b@qq.com
License: MIT
Keywords: wechat itchatui qt weixin ui
Platform: UNKNOWN
Classifier: Development Status :: 3 - Alpha
Classifier: Intended Audience :: Developers
Classifier: Topic :: Software Development :: Libraries :: Python Modules
Classifier: License :: OSI Approved :: MIT License
Classifier: Programming Language :: Python :: 2
Classifier: Programming Language :: Python :: 3
